pyrandwalk/__init__.py
pyrandwalk/__main__.py
pyrandwalk/pyrandwalk_error.py
pyrandwalk/pyrandwalk_obj.py
pyrandwalk/pyrandwalk_param.py
pyrandwalk/pyrandwalk_test.py
pyrandwalk/pyrandwalk_util.py
pyrandwalk-1.1.dist-info/AUTHORS.md
pyrandwalk-1.1.dist-info/LICENSE
pyrandwalk-1.1.dist-info/METADATA
pyrandwalk-1.1.dist-info/WHEEL
pyrandwalk-1.1.dist-info/top_level.txt
pyrandwalk-1.1.dist-info/RECORD
