Metadata-Version: 2.1
Name: pyrandwalk
Version: 1.1
Summary: Python Library for Random Walks
Home-page: https://github.com/sadrasabouri/pyrandwalk
Author: Sadra Sabouri
Author-email: sabouri.sadra@gmail.com
License: MIT
Download-URL: https://github.com/sadrasabouri/pyrandwalk/tarball/v1.1
Project-URL: Source, https://github.com/sadrasabouri/pyrandwalk
Keywords: random-walk markov-chain stochastic-processes
Platform: UNKNOWN
Classifier: Development Status :: 4 - Beta
Classifier: Intended Audience :: Developers
Classifier: Natural Language :: English
Classifier: License :: OSI Approved :: MIT License
Classifier: Operating System :: OS Independent
Classifier: Programming Language :: Python :: 3.5
Classifier: Programming Language :: Python :: 3.6
Classifier: Programming Language :: Python :: 3.7
Classifier: Programming Language :: Python :: 3.8
Classifier: Programming Language :: Python :: 3.9
Classifier: Intended Audience :: Developers
Classifier: Intended Audience :: Education
Classifier: Intended Audience :: End Users/Desktop
Classifier: Intended Audience :: Manufacturing
Classifier: Intended Audience :: Science/Research
Classifier: Topic :: Education
Classifier: Topic :: Scientific/Engineering
Classifier: Topic :: Scientific/Engineering :: Mathematics
Requires-Python: >=3.5
